discolib/__init__.py
discolib/__main__.py
discolib/attr.py
discolib/cobs.py
discolib/core.py
discolib/io.py
discolib/protocol.py
discolib/__pycache__/__init__.cpython-310.pyc
discolib/codegen/clang/disco/attr.c
discolib/codegen/clang/disco/attr.h
discolib/codegen/clang/disco/cobs.c
discolib/codegen/clang/disco/cobs.h
discolib/codegen/clang/disco/command.c
discolib/codegen/clang/disco/command.h
discolib/codegen/clang/disco/disco.c
discolib/codegen/clang/disco/disco.h
discolib/codegen/clang/disco/protocol.c
discolib/codegen/clang/disco/protocol.h
discolib/codegen/clang/disco/types.h
discolib/discogen/bases.py
discolib/discogen/clang.py
discolib/discogen/config.py
discolib/discogen/discogen.py
discolib/examples/serial.py
discolib/examples/stub.py
discolib/examples/tcp.py
discolib-0.1.179.dist-info/METADATA
discolib-0.1.179.dist-info/WHEEL
discolib-0.1.179.dist-info/top_level.txt
discolib-0.1.179.dist-info/RECORD
