Metadata-Version: 2.1
Name: discolib
Version: 0.1.179
Summary: A library for creating high-level interfaces to DISCo-conformant components
Home-page: https://github.com/gavanaken/disco
Author: Greg Van Aken
Author-email: gavanaken@gmail.com
License: MIT
Platform: UNKNOWN
Classifier: Programming Language :: Python :: 3
Classifier: License :: OSI Approved :: MIT License
Classifier: Operating System :: OS Independent
Requires-Python: >=3.6
Requires-Dist: pyserial
Requires-Dist: serialclass
